wifiqr_core
