Metadata-Version: 2.1
Name: wifiqr-core
Version: 1.1.0
Summary: An API to generate a QR-code for your WiFI to let others quickly connect.
Home-page: https://github.com/MoElaSec/WiFiQR_Core
Author: Mo Eltahir
Author-email: mohd.debrecen@gmail.com
License: GPLv3+
Keywords: WiFi,qrcode,pillow
Platform: UNKNOWN
Classifier: Development Status :: 2 - Pre-Alpha
Classifier: Environment :: Console
Classifier: Intended Audience :: End Users/Desktop
Classifier: License :: OSI Approved :: GNU General Public License v3 (GPLv3)
Classifier: Operating System :: OS Independent
Classifier: Topic :: Communications
Classifier: Programming Language :: Python :: 3 :: Only
Classifier: Programming Language :: Python :: 3
Classifier: Programming Language :: Python :: 3.5
Classifier: Programming Language :: Python :: 3.6
Classifier: Programming Language :: Python :: 3.7
Classifier: Programming Language :: Python :: 3.8
Classifier: Programming Language :: Python :: 3.9
Classifier: Topic :: Software Development :: Libraries :: Python Modules
Classifier: Topic :: Scientific/Engineering
